hammock_plot/__init__.py
hammock_plot/figure.py
hammock_plot/main.py
hammock_plot/shapes.py
hammock_plot/unibar.py
hammock_plot/utils.py
hammock_plot/value.py
hammock_plot-1.0.dist-info/LICENSE
hammock_plot-1.0.dist-info/METADATA
hammock_plot-1.0.dist-info/WHEEL
hammock_plot-1.0.dist-info/top_level.txt
hammock_plot-1.0.dist-info/RECORD
