Metadata-Version: 2.1
Name: hammock-plot
Version: 1.0
Summary: Hammock - visualization of categorical or mixed categorical/continuous data
Home-page: https://github.com/TianchengY/hammock_plot
Author: Tiancheng Yang
Author-email: t77yang@uwaterloo.ca
Classifier: Programming Language :: Python :: 3
Classifier: License :: OSI Approved :: MIT License
Classifier: Operating System :: OS Independent
Classifier: Intended Audience :: Science/Research
Requires-Python: >=3.6
License-File: LICENSE
Requires-Dist: matplotlib
Requires-Dist: numpy
Requires-Dist: pandas
